fabric_ops/__init__.py
fabric_ops/auth.py
fabric_ops/base.py
fabric_ops/capacity.py
fabric_ops/capacity_.py
fabric_ops/dax.py
fabric_ops/lakehouse.py
fabric_ops/semantic_model.py
fabric_ops/workspace.py
fabric_ops/config/__init__.py
fabric_ops/services/__init__.py
fabric_ops/services/graph.py
fabric_ops-0.1.5.data/data/requirements.txt
scripts/__init__.py
scripts/get_project_version.py
fabric_ops-0.1.5.dist-info/LICENSE
fabric_ops-0.1.5.dist-info/METADATA
fabric_ops-0.1.5.dist-info/WHEEL
fabric_ops-0.1.5.dist-info/top_level.txt
fabric_ops-0.1.5.dist-info/RECORD
