Metadata-Version: 2.1
Name: fabric-ops
Version: 0.1.5
Summary: English: Fabric-ops is a library for automating tasks with Microsoft Fabric resources. Español: Fabric-ops es una biblioteca para automatizar tareas con los recursos de Microsoft Fabric.
Home-page: https://dalatic.com/fabric-ops
Download-URL: https://github.com/dalatic/fabric-ops
Author: Dalatic S.L
Author-email: info@dalatic.com
License: Proprietary
Classifier: Programming Language :: Python :: 3
Classifier: License :: Other/Proprietary License
Classifier: Operating System :: OS Independent
Requires-Python: >=3.10
License-File: LICENSE
Requires-Dist: azure-core
Requires-Dist: azure-identity
Requires-Dist: azure-storage-blob
Requires-Dist: azure-storage-file-datalake
Requires-Dist: boto3
Requires-Dist: botocore
Requires-Dist: certifi
Requires-Dist: cffi
Requires-Dist: charset-normalizer
Requires-Dist: cryptography
Requires-Dist: idna
Requires-Dist: install
Requires-Dist: isodate
Requires-Dist: jmespath
Requires-Dist: msal
Requires-Dist: msal-extensions
Requires-Dist: packaging
Requires-Dist: portalocker
Requires-Dist: pycparser
Requires-Dist: PyJWT
Requires-Dist: python-dateutil
Requires-Dist: requests
Requires-Dist: s3transfer
Requires-Dist: setuptools
Requires-Dist: six
Requires-Dist: typing-extensions
Requires-Dist: urllib3
Requires-Dist: pandas
Requires-Dist: pyarrow
Requires-Dist: azure-mgmt-resource
Requires-Dist: azure-mgmt-resourcegraph
